swanhelp/__init__.py
swanhelp/_version.py
swanhelp/labextension/package.json
swanhelp/labextension/static/747.cf0588e69accf66cbde4.js
swanhelp/labextension/static/808.27e5a115e667b1332e70.js
swanhelp/labextension/static/remoteEntry.5ad6d7269ef45792cae3.js
swanhelp/labextension/static/style.js
swanhelp/labextension/static/third-party-licenses.json
swanhelp/nbextension/extension.js
swanhelp-3.0.3.data/data/share/jupyter/labextensions/@swan-cern/swanhelp/install.json
swanhelp-3.0.3.data/data/share/jupyter/labextensions/@swan-cern/swanhelp/package.json
swanhelp-3.0.3.data/data/share/jupyter/labextensions/@swan-cern/swanhelp/static/747.cf0588e69accf66cbde4.js
swanhelp-3.0.3.data/data/share/jupyter/labextensions/@swan-cern/swanhelp/static/808.27e5a115e667b1332e70.js
swanhelp-3.0.3.data/data/share/jupyter/labextensions/@swan-cern/swanhelp/static/remoteEntry.5ad6d7269ef45792cae3.js
swanhelp-3.0.3.data/data/share/jupyter/labextensions/@swan-cern/swanhelp/static/style.js
swanhelp-3.0.3.data/data/share/jupyter/labextensions/@swan-cern/swanhelp/static/third-party-licenses.json
swanhelp-3.0.3.dist-info/METADATA
swanhelp-3.0.3.dist-info/WHEEL
swanhelp-3.0.3.dist-info/top_level.txt
swanhelp-3.0.3.dist-info/RECORD
