Metadata-Version: 2.1
Name: swanhelp
Version: 3.0.3
Summary: Help panel for SWAN
Home-page: https://github.com/swan-cern/jupyter-extensions.git
Author: SWAN Admins
License: AGPL-3.0
Keywords: Jupyter,JupyterLab,JupyterLab3,SWAN,CERN
Platform: Linux
Platform: Mac OS X
Platform: Windows
Classifier: Framework :: Jupyter
Classifier: Framework :: Jupyter :: JupyterLab
Classifier: Framework :: Jupyter :: JupyterLab :: 4
Classifier: Framework :: Jupyter :: JupyterLab :: Extensions
Classifier: Framework :: Jupyter :: JupyterLab :: Extensions :: Prebuilt
Classifier: License :: OSI Approved :: GNU Affero General Public License v3
Classifier: Programming Language :: Python
Classifier: Programming Language :: Python :: 3
Classifier: Programming Language :: Python :: 3.8
Classifier: Programming Language :: Python :: 3.9
Classifier: Programming Language :: Python :: 3.10
Classifier: Programming Language :: Python :: 3.11
Requires-Python: >=3.6
Requires-Dist: jupyterlab <5,>=4.0.0
